[
    {
        "ISBN": "0316769177",
        "similarity": 0.9990024937655861,
        "count": 2
    },
    {
        "ISBN": "0316769495",
        "similarity": 0.8,
        "count": 1
    },
    {
        "ISBN": "0316769509",
        "similarity": 0.8,
        "count": 1
    },
    {
        "ISBN": "0440207622",
        "similarity": 0.7998004987531173,
        "count": 1
    },
    {
        "ISBN": "0385299079",
        "similarity": 0.7998004987531173,
        "count": 1
    },
    {
        "ISBN": "0440214114",
        "similarity": 0.7996009975062345,
        "count": 1
    },
    {
        "ISBN": "0385306059",
        "similarity": 0.7994014962593516,
        "count": 1
    },
    {
        "ISBN": "044011585X",
        "similarity": 0.7992019950124689,
        "count": 1
    },
    {
        "ISBN": "0385311923",
        "similarity": 0.7992019950124689,
        "count": 1
    },
    {
        "ISBN": "0385315309",
        "similarity": 0.7992019950124689,
        "count": 1
    },
    {
        "ISBN": "0671702505",
        "similarity": 0.7,
        "count": 1
    },
    {
        "ISBN": "038531292X",
        "similarity": 0.6997007481296759,
        "count": 1
    },
    {
        "ISBN": "0821746480",
        "similarity": 0.6997007481296759,
        "count": 1
    },
    {
        "ISBN": "0553250256",
        "similarity": 0.6993017456359103,
        "count": 1
    },
    {
        "ISBN": "0679732411",
        "similarity": 0.5333333333333333,
        "count": 1
    },
    {
        "ISBN": "0440204321",
        "similarity": 0.5331338320864505,
        "count": 1
    },
    {
        "ISBN": "0671536621",
        "similarity": 0.5329343308395678,
        "count": 1
    },
    {
        "ISBN": "0394557433",
        "similarity": 0.5328345802161263,
        "count": 1
    },
    {
        "ISBN": "0671536613",
        "similarity": 0.5328345802161263,
        "count": 1
    }
]